add2winpath/LICENSE
add2winpath/README.MD
add2winpath/__init__.py
add2winpath/requirements.txt
add2winpath/thirdparty.json
add2winpath-0.10.dist-info/LICENSE.rst
add2winpath-0.10.dist-info/METADATA
add2winpath-0.10.dist-info/WHEEL
add2winpath-0.10.dist-info/top_level.txt
add2winpath-0.10.dist-info/RECORD
