Metadata-Version: 2.1
Name: add2winpath
Version: 0.10
Summary: Adds/removes folders to the PATH on Windows (Current User/All Users). It doesn't spoil paths with variables (e.g. %windir%\system32)
Home-page: https://github.com/hansalemaos/add2winpath
Author: Johannes Fischer
Author-email: <aulasparticularesdealemaosp@gmail.com>
License: MIT
Keywords: path,windows,add,remove
Classifier: Development Status :: 4 - Beta
Classifier: Programming Language :: Python :: 3 :: Only
Classifier: Programming Language :: Python :: 3.10
Classifier: Topic :: Scientific/Engineering :: Visualization
Classifier: Topic :: Software Development :: Libraries :: Python Modules
Classifier: Topic :: Utilities
License-File: LICENSE.rst
Requires-Dist: list-all-files-recursively
Requires-Dist: reggisearch
Requires-Dist: touchtouch
